<?xml version="1.0" ?>
<movies>
  <movie>
    <title>30 Minutes or Less (2011)</title>
    <link>http://10.1.1.1/data/English%20Movies%20%281080p%29/%282011%29%201080p/30%20Minutes%20or%20Less%20%282011%29%201080p/30%20Minutes%20or%20Less%20%282011%29%201080p%20BluRay%20x265%20HEVC%2010bit%20AAC%205.1%20MSubs-Prof.mkv</link>
    <thumbnail>http://10.1.1.1/data/English%20Movies%20%281080p%29/%282011%29%201080p/30%20Minutes%20or%20Less%20%282011%29%201080p/a_AL_.jpg</thumbnail>
    <fanart>http://10.1.1.1/data/English%20Movies%20%281080p%29/%282011%29%201080p/30%20Minutes%20or%20Less%20%282011%29%201080p/a_AL_.jpg</fanart>
  </movie>
  <movie>
    <title>50-50 (2011)</title>
    <link>http://10.1.1.1/data/English%20Movies%20%281080p%29/%282011%29%201080p/50-50%20%282011%29%201080p/50-50%20%282011%29%201080p%20BluRay%20x265%20HEVC%2010bit%20AAC%205.1%20MSubs-Tigole.mkv</link>
    <thumbnail>http://10.1.1.1/data/English%20Movies%20%281080p%29/%282011%29%201080p/50-50%20%282011%29%201080p/a_AL_.jpg</thumbnail>
    <fanart>http://10.1.1.1/data/English%20Movies%20%281080p%29/%282011%29%201080p/50-50%20%282011%29%201080p/a_AL_.jpg</fanart>
  </movie>
  <movie>
    <title>A Dangerous Method (2011)</title>
    <link>http://10.1.1.1/data/English%20Movies%20%281080p%29/%282011%29%201080p/A%20Dangerous%20Method%20%282011%29%201080p/A%20Dangerous%20Method%20%282011%29%201080p%20BluRay%20x265%20HEVC%2010bit%20AAC%205.1%20MSubs-Tigole.mkv</link>
    <thumbnail>http://10.1.1.1/data/English%20Movies%20%281080p%29/%282011%29%201080p/A%20Dangerous%20Method%20%282011%29%201080p/a_AL_.jpg</thumbnail>
    <fanart>http://10.1.1.1/data/English%20Movies%20%281080p%29/%282011%29%201080p/A%20Dangerous%20Method%20%282011%29%201080p/a_AL_.jpg</fanart>
  </movie>
  <movie>
    <title>A Lonely Place to Die (2011)</title>
    <link>http://10.1.1.1/data/English%20Movies%20%281080p%29/%282011%29%201080p/A%20Lonely%20Place%20to%20Die%20%282011%29%201080p/A.Lonely.Place.to.Die.2011.1080p.BluRay.x264.YIFY.mp4</link>
    <thumbnail>http://10.1.1.1/data/English%20Movies%20%281080p%29/%282011%29%201080p/A%20Lonely%20Place%20to%20Die%20%282011%29%201080p/a08_.jpg</thumbnail>
    <fanart>http://10.1.1.1/data/English%20Movies%20%281080p%29/%282011%29%201080p/A%20Lonely%20Place%20to%20Die%20%282011%29%201080p/a08_.jpg</fanart>
  </movie>
  <movie>
    <title>Another Earth (2011)</title>
    <link>http://10.1.1.1/data/English%20Movies%20%281080p%29/%282011%29%201080p/Another%20Earth%20%282011%29%201080p/Another%20Earth%20%282011%29%201080p%20BluRay%20x265%20HEVC%2010bit%20AAC%205.1%20MSubs-Tigole.mkv</link>
    <thumbnail>http://10.1.1.1/data/English%20Movies%20%281080p%29/%282011%29%201080p/Another%20Earth%20%282011%29%201080p/a_AL_.jpg</thumbnail>
    <fanart>http://10.1.1.1/data/English%20Movies%20%281080p%29/%282011%29%201080p/Another%20Earth%20%282011%29%201080p/a_AL_.jpg</fanart>
  </movie>
  <movie>
    <title>Bad Teacher (2011)</title>
    <link>http://10.1.1.1/data/English%20Movies%20%281080p%29/%282011%29%201080p/Bad%20Teacher%20%282011%29%201080p/Bad%20Teacher%20%282011%29%20UNRATED%201080p%20BluRay%20x265%20HEVC%2010bit%20AAC%205.1%20ESub-PSA.mkv</link>
    <thumbnail>http://10.1.1.1/data/English%20Movies%20%281080p%29/%282011%29%201080p/Bad%20Teacher%20%282011%29%201080p/a_AL_.jpg</thumbnail>
    <fanart>http://10.1.1.1/data/English%20Movies%20%281080p%29/%282011%29%201080p/Bad%20Teacher%20%282011%29%201080p/a_AL_.jpg</fanart>
  </movie>
  <movie>
    <title>Battle Los Angeles (2011)</title>
    <link>http://10.1.1.1/data/English%20Movies%20%281080p%29/%282011%29%201080p/Battle%20Los%20Angeles%20%282011%29%201080p/Battle%20Los%20Angeles%20%282011%29%201080p%20BluRay%20x265%20HEVC%2010bit%20AAC%205.1%20ESub-pav69.mkv</link>
    <thumbnail>http://10.1.1.1/data/English%20Movies%20%281080p%29/%282011%29%201080p/Battle%20Los%20Angeles%20%282011%29%201080p/a_AL_.jpg</thumbnail>
    <fanart>http://10.1.1.1/data/English%20Movies%20%281080p%29/%282011%29%201080p/Battle%20Los%20Angeles%20%282011%29%201080p/a_AL_.jpg</fanart>
  </movie>
  <movie>
    <title>Bernie (2011)</title>
    <link>http://10.1.1.1/data/English%20Movies%20%281080p%29/%282011%29%201080p/Bernie%20%282011%29%201080p/Bernie%20%282011%29%20%5B1080p%5D.mp4</link>
    <thumbnail>http://10.1.1.1/data/English%20Movies%20%281080p%29/%282011%29%201080p/Bernie%20%282011%29%201080p/a074.jpg</thumbnail>
    <fanart>http://10.1.1.1/data/English%20Movies%20%281080p%29/%282011%29%201080p/Bernie%20%282011%29%201080p/a074.jpg</fanart>
  </movie>
  <movie>
    <title>Blitz (2011)</title>
    <link>http://10.1.1.1/data/English%20Movies%20%281080p%29/%282011%29%201080p/Blitz%20%282011%29%201080p/Blitz.2011.1080p.BluRay.H264.AAC-RARBG.mp4</link>
    <thumbnail>http://10.1.1.1/data/English%20Movies%20%281080p%29/%282011%29%201080p/Blitz%20%282011%29%201080p/a_AL_.jpg</thumbnail>
    <fanart>http://10.1.1.1/data/English%20Movies%20%281080p%29/%282011%29%201080p/Blitz%20%282011%29%201080p/a_AL_.jpg</fanart>
  </movie>
  <movie>
    <title>Blitz (2011)</title>
    <link>http://10.1.1.1/data/English%20Movies%20%281080p%29/%282011%29%201080p/Blitz%20%282011%29%201080p%20%5BDual%20Audio%5D/Blitz%20%282011%29%201080p%20BluRay%20x265%20HEVC%20ESub%20%5BDual%20Audio%5D%5BHindi%205.1%2BEnglish%205.1%5D%20-mkvC.mkv</link>
    <thumbnail>http://10.1.1.1/data/English%20Movies%20%281080p%29/%282011%29%201080p/Blitz%20%282011%29%201080p%20%5BDual%20Audio%5D/a_AL_.jpg</thumbnail>
    <fanart>http://10.1.1.1/data/English%20Movies%20%281080p%29/%282011%29%201080p/Blitz%20%282011%29%201080p%20%5BDual%20Audio%5D/a_AL_.jpg</fanart>
  </movie>
  <movie>
    <title>Bridesmaids (2011)</title>
    <link>http://10.1.1.1/data/English%20Movies%20%281080p%29/%282011%29%201080p/Bridesmaids%20%282011%29%201080p/Bridesmaids.2011.EXTENDED.1080p.BluRay.H264.AAC-RARBG.mp4</link>
    <thumbnail>http://10.1.1.1/data/English%20Movies%20%281080p%29/%282011%29%201080p/Bridesmaids%20%282011%29%201080p/a_AL_.jpg</thumbnail>
    <fanart>http://10.1.1.1/data/English%20Movies%20%281080p%29/%282011%29%201080p/Bridesmaids%20%282011%29%201080p/a_AL_.jpg</fanart>
  </movie>
  <movie>
    <title>Captain America-The First Avenger (2011)</title>
    <link>http://10.1.1.1/data/English%20Movies%20%281080p%29/%282011%29%201080p/Captain%20America-The%20First%20Avenger%20%282011%29%201080p/Captain.America.The.First.Avenger.2011.1080p.BluRay.AC3.x264.ESub-ETRG.mkv</link>
    <thumbnail>http://10.1.1.1/data/English%20Movies%20%281080p%29/%282011%29%201080p/Captain%20America-The%20First%20Avenger%20%282011%29%201080p/a6870.jpg</thumbnail>
    <fanart>http://10.1.1.1/data/English%20Movies%20%281080p%29/%282011%29%201080p/Captain%20America-The%20First%20Avenger%20%282011%29%201080p/a6870.jpg</fanart>
  </movie>
  <movie>
    <title>Colombiana (2011)</title>
    <link>http://10.1.1.1/data/English%20Movies%20%281080p%29/%282011%29%201080p/Colombiana%20%282011%29%201080p/Colombiana.2011.UNRATED.1080p.BluRay.H264.AAC-RARBG.mp4</link>
    <thumbnail>http://10.1.1.1/data/English%20Movies%20%281080p%29/%282011%29%201080p/Colombiana%20%282011%29%201080p/a_AL_.jpg</thumbnail>
    <fanart>http://10.1.1.1/data/English%20Movies%20%281080p%29/%282011%29%201080p/Colombiana%20%282011%29%201080p/a_AL_.jpg</fanart>
  </movie>
  <movie>
    <title>Conan the Barbarian (2011)</title>
    <link>http://10.1.1.1/data/English%20Movies%20%281080p%29/%282011%29%201080p/Conan%20the%20Barbarian%20%282011%29%201080p/Conan.The.Barbarian.2011.1080p.BluRay.H264.AAC-RARBG.mp4</link>
    <thumbnail>http://10.1.1.1/data/English%20Movies%20%281080p%29/%282011%29%201080p/Conan%20the%20Barbarian%20%282011%29%201080p/a_AL_.jpg</thumbnail>
    <fanart>http://10.1.1.1/data/English%20Movies%20%281080p%29/%282011%29%201080p/Conan%20the%20Barbarian%20%282011%29%201080p/a_AL_.jpg</fanart>
  </movie>
  <movie>
    <title>Contagion (2011)</title>
    <link>http://10.1.1.1/data/English%20Movies%20%281080p%29/%282011%29%201080p/Contagion%20%282011%29%201080p/Contagion%20%282011%29%201080p%20BluRay%20x265%20HEVC%2010bit%20AAC%205.1%20MSubs-Tigole.mkv</link>
    <thumbnail>http://10.1.1.1/data/English%20Movies%20%281080p%29/%282011%29%201080p/Contagion%20%282011%29%201080p/a_AL_.jpg</thumbnail>
    <fanart>http://10.1.1.1/data/English%20Movies%20%281080p%29/%282011%29%201080p/Contagion%20%282011%29%201080p/a_AL_.jpg</fanart>
  </movie>
  <movie>
    <title>Coriolanus (2011)</title>
    <link>http://10.1.1.1/data/English%20Movies%20%281080p%29/%282011%29%201080p/Coriolanus%20%282011%29%201080p/Coriolanus%20%282011%29%20%5B1080p%5D.mp4</link>
    <thumbnail>http://10.1.1.1/data/English%20Movies%20%281080p%29/%282011%29%201080p/Coriolanus%20%282011%29%201080p/a40_SY720_.jpg</thumbnail>
    <fanart>http://10.1.1.1/data/English%20Movies%20%281080p%29/%282011%29%201080p/Coriolanus%20%282011%29%201080p/a40_SY720_.jpg</fanart>
  </movie>
  <movie>
    <title>Cowboys &amp; Aliens (2011)</title>
    <link>http://10.1.1.1/data/English%20Movies%20%281080p%29/%282011%29%201080p/Cowboys%20%26%20Aliens%20%282011%29%201080p/Cowboys%20%26%20Aliens%20%282011%29%20Extended%201080p%20BluRay%20x265%20HEVC%2010bit%205.1%20MSubs-Tigole.mkv</link>
    <thumbnail>http://10.1.1.1/data/English%20Movies%20%281080p%29/%282011%29%201080p/Cowboys%20%26%20Aliens%20%282011%29%201080p/a_AL_.jpg</thumbnail>
    <fanart>http://10.1.1.1/data/English%20Movies%20%281080p%29/%282011%29%201080p/Cowboys%20%26%20Aliens%20%282011%29%201080p/a_AL_.jpg</fanart>
  </movie>
  <movie>
    <title>Crazy, Stupid, Love (2011)</title>
    <link>http://10.1.1.1/data/English%20Movies%20%281080p%29/%282011%29%201080p/Crazy%2C%20Stupid%2C%20Love.%20%282011%29%201080p/Crazy%2C%20Stupid%2C%20Love%20%282011%29%201080p%20BluRay%20x265%20HEVC%2010bit%20AAC%205.1%20MSubs-Tigole.mkv</link>
    <thumbnail>http://10.1.1.1/data/English%20Movies%20%281080p%29/%282011%29%201080p/Crazy%2C%20Stupid%2C%20Love.%20%282011%29%201080p/a_AL_.jpg</thumbnail>
    <fanart>http://10.1.1.1/data/English%20Movies%20%281080p%29/%282011%29%201080p/Crazy%2C%20Stupid%2C%20Love.%20%282011%29%201080p/a_AL_.jpg</fanart>
  </movie>
  <movie>
    <title>Detachment (2011)</title>
    <link>http://10.1.1.1/data/English%20Movies%20%281080p%29/%282011%29%201080p/Detachment%20%282011%29%201080p/Detachment.2011.1080p.BluRay.H264.AAC-RARBG.mp4</link>
    <thumbnail>http://10.1.1.1/data/English%20Movies%20%281080p%29/%282011%29%201080p/Detachment%20%282011%29%201080p/a_AL_.jpg</thumbnail>
    <fanart>http://10.1.1.1/data/English%20Movies%20%281080p%29/%282011%29%201080p/Detachment%20%282011%29%201080p/a_AL_.jpg</fanart>
  </movie>
  <movie>
    <title>Dolphin Tale (2011)</title>
    <link>http://10.1.1.1/data/English%20Movies%20%281080p%29/%282011%29%201080p/Dolphin%20Tale%20%282011%29%201080p/Dolphin.Tale.2011.1080p.BluRay.H264.AAC-RARBG.mp4</link>
    <thumbnail>http://10.1.1.1/data/English%20Movies%20%281080p%29/%282011%29%201080p/Dolphin%20Tale%20%282011%29%201080p/a_AL_.jpg</thumbnail>
    <fanart>http://10.1.1.1/data/English%20Movies%20%281080p%29/%282011%29%201080p/Dolphin%20Tale%20%282011%29%201080p/a_AL_.jpg</fanart>
  </movie>
  <movie>
    <title>Dream House (2011)</title>
    <link>http://10.1.1.1/data/English%20Movies%20%281080p%29/%282011%29%201080p/Dream%20House%20%282011%29%201080p/Dream%20House%20%282011%29%201080p%20BluRay%20x265%20HEVC%2010bit%20AAC%205.1%20MSubs-Tigole.mkv</link>
    <thumbnail>http://10.1.1.1/data/English%20Movies%20%281080p%29/%282011%29%201080p/Dream%20House%20%282011%29%201080p/a_AL_.jpg</thumbnail>
    <fanart>http://10.1.1.1/data/English%20Movies%20%281080p%29/%282011%29%201080p/Dream%20House%20%282011%29%201080p/a_AL_.jpg</fanart>
  </movie>
  <movie>
    <title>Drive (2011)</title>
    <link>http://10.1.1.1/data/English%20Movies%20%281080p%29/%282011%29%201080p/Drive%20%282011%29%201080p/Drive%20%282011%29%201080p%20BluRay%20x265%20HEVC%2010bit%20AAC%207.1%20MSubs-Tigole.mkv</link>
    <thumbnail>http://10.1.1.1/data/English%20Movies%20%281080p%29/%282011%29%201080p/Drive%20%282011%29%201080p/a_AL_.jpg</thumbnail>
    <fanart>http://10.1.1.1/data/English%20Movies%20%281080p%29/%282011%29%201080p/Drive%20%282011%29%201080p/a_AL_.jpg</fanart>
  </movie>
  <movie>
    <title>Drive Angry (2011)</title>
    <link>http://10.1.1.1/data/English%20Movies%20%281080p%29/%282011%29%201080p/Drive%20Angry%20%282011%29%201080p/Drive.Angry.2011.1080p.BluRay.H264.AAC-RARBG.mp4</link>
    <thumbnail>http://10.1.1.1/data/English%20Movies%20%281080p%29/%282011%29%201080p/Drive%20Angry%20%282011%29%201080p/a_AL_.jpg</thumbnail>
    <fanart>http://10.1.1.1/data/English%20Movies%20%281080p%29/%282011%29%201080p/Drive%20Angry%20%282011%29%201080p/a_AL_.jpg</fanart>
  </movie>
  <movie>
    <title>Extremely Loud &amp; Incredibly Close (2011)</title>
    <link>http://10.1.1.1/data/English%20Movies%20%281080p%29/%282011%29%201080p/Extremely%20Loud%20%26%20Incredibly%20Close%20%282011%29%201080p/Extremely%20Loud%20%26%20Incredibly%20Close%20%282011%29%201080p%20BluRay%20x265%20HEVC%20AAC%205.1%20MSubs-Tigole.mkv</link>
    <thumbnail>http://10.1.1.1/data/English%20Movies%20%281080p%29/%282011%29%201080p/Extremely%20Loud%20%26%20Incredibly%20Close%20%282011%29%201080p/a_AL_.jpg</thumbnail>
    <fanart>http://10.1.1.1/data/English%20Movies%20%281080p%29/%282011%29%201080p/Extremely%20Loud%20%26%20Incredibly%20Close%20%282011%29%201080p/a_AL_.jpg</fanart>
  </movie>
  <movie>
    <title>Fast Five (2011)</title>
    <link>http://10.1.1.1/data/English%20Movies%20%281080p%29/%282011%29%201080p/Fast%20Five%20%282011%29%201080p/Fast%20Five%20%282011%29%201080p%20BluRay%20x265%20HEVC%2010bit%20AAC%207.1%20MSubs-Prof.mkv</link>
    <thumbnail>http://10.1.1.1/data/English%20Movies%20%281080p%29/%282011%29%201080p/Fast%20Five%20%282011%29%201080p/a_AL_.jpg</thumbnail>
    <fanart>http://10.1.1.1/data/English%20Movies%20%281080p%29/%282011%29%201080p/Fast%20Five%20%282011%29%201080p/a_AL_.jpg</fanart>
  </movie>
  <movie>
    <title>Final Destination 5 (2011)</title>
    <link>http://10.1.1.1/data/English%20Movies%20%281080p%29/%282011%29%201080p/Final%20Destination%205%20%282011%29%201080p%20%5BDual%20Audio%5D/Final%20Destination%205%20%282011%29%201080p%20BluRay%20x265%20HEVC%20MSubs%20%5BDual%20Audio%5D%5BHindi%205.1%2BEnglish%205.1%5D%20-OlaM.mkv</link>
    <thumbnail>http://10.1.1.1/data/English%20Movies%20%281080p%29/%282011%29%201080p/Final%20Destination%205%20%282011%29%201080p%20%5BDual%20Audio%5D/a_AL_.jpg</thumbnail>
    <fanart>http://10.1.1.1/data/English%20Movies%20%281080p%29/%282011%29%201080p/Final%20Destination%205%20%282011%29%201080p%20%5BDual%20Audio%5D/a_AL_.jpg</fanart>
  </movie>
  <movie>
    <title>Friends with Benefits (2011)</title>
    <link>http://10.1.1.1/data/English%20Movies%20%281080p%29/%282011%29%201080p/Friends%20with%20Benefits%20%282011%29%201080p/Friends%20with%20Benefits%20%282011%29%201080p%20BluRay%20x265%20HEVC%20AAC%205.1%20MSubs-LordVako.mkv</link>
    <thumbnail>http://10.1.1.1/data/English%20Movies%20%281080p%29/%282011%29%201080p/Friends%20with%20Benefits%20%282011%29%201080p/a_AL_.jpg</thumbnail>
    <fanart>http://10.1.1.1/data/English%20Movies%20%281080p%29/%282011%29%201080p/Friends%20with%20Benefits%20%282011%29%201080p/a_AL_.jpg</fanart>
  </movie>
  <movie>
    <title>Fright Night (2011)</title>
    <link>http://10.1.1.1/data/English%20Movies%20%281080p%29/%282011%29%201080p/Fright%20Night%20%282011%29%201080p/Fright%20Night%20%282011%29%201080p%20BluRay%20x265%20HEVC%2010bit%20AAC%207.1%20MSubs-Tigole.mkv</link>
    <thumbnail>http://10.1.1.1/data/English%20Movies%20%281080p%29/%282011%29%201080p/Fright%20Night%20%282011%29%201080p/a_AL_.jpg</thumbnail>
    <fanart>http://10.1.1.1/data/English%20Movies%20%281080p%29/%282011%29%201080p/Fright%20Night%20%282011%29%201080p/a_AL_.jpg</fanart>
  </movie>
  <movie>
    <title>Ghost Rider-Spirit of Vengeance (2011)</title>
    <link>http://10.1.1.1/data/English%20Movies%20%281080p%29/%282011%29%201080p/Ghost%20Rider-Spirit%20of%20Vengeance%20%282011%29%201080p/Ghost.Rider.Spirit.Of.Vengeance.2011.1080p.BluRay.H264.AAC-RARBG.mp4</link>
    <thumbnail>http://10.1.1.1/data/English%20Movies%20%281080p%29/%282011%29%201080p/Ghost%20Rider-Spirit%20of%20Vengeance%20%282011%29%201080p/a_AL_.jpg</thumbnail>
    <fanart>http://10.1.1.1/data/English%20Movies%20%281080p%29/%282011%29%201080p/Ghost%20Rider-Spirit%20of%20Vengeance%20%282011%29%201080p/a_AL_.jpg</fanart>
  </movie>
  <movie>
    <title>Goon (2011)</title>
    <link>http://10.1.1.1/data/English%20Movies%20%281080p%29/%282011%29%201080p/Goon%20%282011%29%201080p/Goon%20%282011%29%201080p%20BluRay%20x265%20HEVC%2010bit%20AAC%205.1%20MSubs-r00t.mkv</link>
    <thumbnail>http://10.1.1.1/data/English%20Movies%20%281080p%29/%282011%29%201080p/Goon%20%282011%29%201080p/a_AL_.jpg</thumbnail>
    <fanart>http://10.1.1.1/data/English%20Movies%20%281080p%29/%282011%29%201080p/Goon%20%282011%29%201080p/a_AL_.jpg</fanart>
  </movie>
  <movie>
    <title>Green Lantern (2011)</title>
    <link>http://10.1.1.1/data/English%20Movies%20%281080p%29/%282011%29%201080p/Green%20Lantern%20%282011%29%201080p/Green%20Lantern%20%282011%29%20Extended%201080p%20BluRay%20x265%20HEVC%2010bit%205.1%20MSubs-Tigole.mkv</link>
    <thumbnail>http://10.1.1.1/data/English%20Movies%20%281080p%29/%282011%29%201080p/Green%20Lantern%20%282011%29%201080p/a_AL_.jpg</thumbnail>
    <fanart>http://10.1.1.1/data/English%20Movies%20%281080p%29/%282011%29%201080p/Green%20Lantern%20%282011%29%201080p/a_AL_.jpg</fanart>
  </movie>
  <movie>
    <title>Hall Pass (2011)</title>
    <link>http://10.1.1.1/data/English%20Movies%20%281080p%29/%282011%29%201080p/Hall%20Pass%20%282011%29%201080p/Hall%20Pass%20%282011%29%20Extended%201080p%20BluRay%20x265%20HEVC%2010bit%20AAC%205.1%20MSubs-Prof.mkv</link>
    <thumbnail>http://10.1.1.1/data/English%20Movies%20%281080p%29/%282011%29%201080p/Hall%20Pass%20%282011%29%201080p/a_AL_.jpg</thumbnail>
    <fanart>http://10.1.1.1/data/English%20Movies%20%281080p%29/%282011%29%201080p/Hall%20Pass%20%282011%29%201080p/a_AL_.jpg</fanart>
  </movie>
  <movie>
    <title>Hanna (2011)</title>
    <link>http://10.1.1.1/data/English%20Movies%20%281080p%29/%282011%29%201080p/Hanna%20%282011%29%201080p/Hanna%20%282011%29%201080p%20BluRay%20x265%20HEVC%2010bit%20AAC%205.1%20MSubs-Tigole.mkv</link>
    <thumbnail>http://10.1.1.1/data/English%20Movies%20%281080p%29/%282011%29%201080p/Hanna%20%282011%29%201080p/a_AL_.jpg</thumbnail>
    <fanart>http://10.1.1.1/data/English%20Movies%20%281080p%29/%282011%29%201080p/Hanna%20%282011%29%201080p/a_AL_.jpg</fanart>
  </movie>
  <movie>
    <title>Harry Potter and the Deathly Hallows-Part 2 (2011)</title>
    <link>http://10.1.1.1/data/English%20Movies%20%281080p%29/%282011%29%201080p/Harry%20Potter%20and%20the%20Deathly%20Hallows-Part%202%20%282011%29%201080p/Harry%20Potter%20and%20the%20Deathly%20Hallows-Part%202%20%282011%29%201080p%20BluRay%20x265%20HEVC%205.1%20MSubs-Tigole.mkv</link>
    <thumbnail>http://10.1.1.1/data/English%20Movies%20%281080p%29/%282011%29%201080p/Harry%20Potter%20and%20the%20Deathly%20Hallows-Part%202%20%282011%29%201080p/a_AL_.jpg</thumbnail>
    <fanart>http://10.1.1.1/data/English%20Movies%20%281080p%29/%282011%29%201080p/Harry%20Potter%20and%20the%20Deathly%20Hallows-Part%202%20%282011%29%201080p/a_AL_.jpg</fanart>
  </movie>
  <movie>
    <title>Haywire (2011)</title>
    <link>http://10.1.1.1/data/English%20Movies%20%281080p%29/%282011%29%201080p/Haywire%20%282011%29%201080p%20%5BDual%20Audio%5D/Haywire%20%282011%29%201080p%20BluRay%20x265%20HEVC%20ESub%20%5BDual%20Audio%5D%5BHindi%202.0%2BEnglish%205.1%5D%20-mkvC.mkv</link>
    <thumbnail>http://10.1.1.1/data/English%20Movies%20%281080p%29/%282011%29%201080p/Haywire%20%282011%29%201080p%20%5BDual%20Audio%5D/a_AL_.jpg</thumbnail>
    <fanart>http://10.1.1.1/data/English%20Movies%20%281080p%29/%282011%29%201080p/Haywire%20%282011%29%201080p%20%5BDual%20Audio%5D/a_AL_.jpg</fanart>
  </movie>
  <movie>
    <title>Headhunters (2011)</title>
    <link>http://10.1.1.1/data/English%20Movies%20%281080p%29/%282011%29%201080p/Headhunters%20%282011%29%201080p/Headhunters.2011.1080p.BluRay.H264.AAC-RARBG.mp4</link>
    <thumbnail>http://10.1.1.1/data/English%20Movies%20%281080p%29/%282011%29%201080p/Headhunters%20%282011%29%201080p/a_AL_.jpg</thumbnail>
    <fanart>http://10.1.1.1/data/English%20Movies%20%281080p%29/%282011%29%201080p/Headhunters%20%282011%29%201080p/a_AL_.jpg</fanart>
  </movie>
  <movie>
    <title>Horrible Bosses (2011)</title>
    <link>http://10.1.1.1/data/English%20Movies%20%281080p%29/%282011%29%201080p/Horrible%20Bosses%20%282011%29%201080p/Horrible.Bosses.2011.EXTENDED.1080p.BluRay.H264.AAC-RARBG.mp4</link>
    <thumbnail>http://10.1.1.1/data/English%20Movies%20%281080p%29/%282011%29%201080p/Horrible%20Bosses%20%282011%29%201080p/a_AL_.jpg</thumbnail>
    <fanart>http://10.1.1.1/data/English%20Movies%20%281080p%29/%282011%29%201080p/Horrible%20Bosses%20%282011%29%201080p/a_AL_.jpg</fanart>
  </movie>
  <movie>
    <title>Hugo (2011)</title>
    <link>http://10.1.1.1/data/English%20Movies%20%281080p%29/%282011%29%201080p/Hugo%20%282011%29%201080p%20%5BDual%20Audio%5D/Hugo%20%282011%29%201080p%20BluRay%20x265%20HEVC%20ESub%20%5BDual%20Audio%5D%5BHindi%205.1%2BEnglish%205.1%5D%20-mkvC.mkv</link>
    <thumbnail>http://10.1.1.1/data/English%20Movies%20%281080p%29/%282011%29%201080p/Hugo%20%282011%29%201080p%20%5BDual%20Audio%5D/a_AL_.jpg</thumbnail>
    <fanart>http://10.1.1.1/data/English%20Movies%20%281080p%29/%282011%29%201080p/Hugo%20%282011%29%201080p%20%5BDual%20Audio%5D/a_AL_.jpg</fanart>
  </movie>
  <movie>
    <title>I Am Number Four (2011)</title>
    <link>http://10.1.1.1/data/English%20Movies%20%281080p%29/%282011%29%201080p/I%20Am%20Number%20Four%20%282011%29%201080p/I%20Am%20Number%20Four%20%282011%29%201080p%20BluRay%20x265%20HEVC%2010bit%20AAC%205.1%20MSubs-Tigole.mkv</link>
    <thumbnail>http://10.1.1.1/data/English%20Movies%20%281080p%29/%282011%29%201080p/I%20Am%20Number%20Four%20%282011%29%201080p/a_AL_.jpg</thumbnail>
    <fanart>http://10.1.1.1/data/English%20Movies%20%281080p%29/%282011%29%201080p/I%20Am%20Number%20Four%20%282011%29%201080p/a_AL_.jpg</fanart>
  </movie>
  <movie>
    <title>Immortals (2011)</title>
    <link>http://10.1.1.1/data/English%20Movies%20%281080p%29/%282011%29%201080p/Immortals%20%282011%29%201080p%20%5BDual%20Audio%5D/Immortals%20%282011%29%201080p%20BluRay%20x265%20HEVC%20ESub%20%5BDual%20Audio%5D%5BHindi%205.1%2BEnglish%205.1%5D%20-mkvC.mkv</link>
    <thumbnail>http://10.1.1.1/data/English%20Movies%20%281080p%29/%282011%29%201080p/Immortals%20%282011%29%201080p%20%5BDual%20Audio%5D/a_AL_.jpg</thumbnail>
    <fanart>http://10.1.1.1/data/English%20Movies%20%281080p%29/%282011%29%201080p/Immortals%20%282011%29%201080p%20%5BDual%20Audio%5D/a_AL_.jpg</fanart>
  </movie>
  <movie>
    <title>In Time (2011)</title>
    <link>http://10.1.1.1/data/English%20Movies%20%281080p%29/%282011%29%201080p/In%20Time%20%282011%29%201080p/In%20Time%20%282011%29%201080p%20BluRay%20x265%20HEVC%2010bit%20AAC%205.1%20MSubs-Tigole.mkv</link>
    <thumbnail>http://10.1.1.1/data/English%20Movies%20%281080p%29/%282011%29%201080p/In%20Time%20%282011%29%201080p/a_AL_.jpg</thumbnail>
    <fanart>http://10.1.1.1/data/English%20Movies%20%281080p%29/%282011%29%201080p/In%20Time%20%282011%29%201080p/a_AL_.jpg</fanart>
  </movie>
  <movie>
    <title>In Time (2011)</title>
    <link>http://10.1.1.1/data/English%20Movies%20%281080p%29/%282011%29%201080p/In%20Time%20%282011%29%201080p%20%5BDual%20Audio%5D/In%20Time%20%282011%29%201080p%20BluRay%20x265%20HEVC%20ESub%20%5BDual%20Audio%5D%5BHindi%202.0%2BEnglish%205.1%5D%20-mkvC.mkv</link>
    <thumbnail>http://10.1.1.1/data/English%20Movies%20%281080p%29/%282011%29%201080p/In%20Time%20%282011%29%201080p%20%5BDual%20Audio%5D/a_AL_.jpg</thumbnail>
    <fanart>http://10.1.1.1/data/English%20Movies%20%281080p%29/%282011%29%201080p/In%20Time%20%282011%29%201080p%20%5BDual%20Audio%5D/a_AL_.jpg</fanart>
  </movie>
  <movie>
    <title>Intruders (2011)</title>
    <link>http://10.1.1.1/data/English%20Movies%20%281080p%29/%282011%29%201080p/Intruders%20%282011%29%201080p/Intruders.2011.1080p.BluRay.x264.YIFY.mp4</link>
    <thumbnail>http://10.1.1.1/data/English%20Movies%20%281080p%29/%282011%29%201080p/Intruders%20%282011%29%201080p/ar41.jpg</thumbnail>
    <fanart>http://10.1.1.1/data/English%20Movies%20%281080p%29/%282011%29%201080p/Intruders%20%282011%29%201080p/ar41.jpg</fanart>
  </movie>
  <movie>
    <title>Isle of Dogs (2011)</title>
    <link>http://10.1.1.1/data/English%20Movies%20%281080p%29/%282011%29%201080p/Isle%20of%20Dogs%20%282011%29%201080p/Isle.of.Dogs.2011.1080p.mp4</link>
    <thumbnail>http://10.1.1.1/data/English%20Movies%20%281080p%29/%282011%29%201080p/Isle%20of%20Dogs%20%282011%29%201080p/download.jpg</thumbnail>
    <fanart>http://10.1.1.1/data/English%20Movies%20%281080p%29/%282011%29%201080p/Isle%20of%20Dogs%20%282011%29%201080p/download.jpg</fanart>
  </movie>
  <movie>
    <title>Jane Eyre (2011)</title>
    <link>http://10.1.1.1/data/English%20Movies%20%281080p%29/%282011%29%201080p/Jane%20Eyre%20%282011%29%201080p/Jane.Eyre.2011.1080p.BluRay.H264.AAC-RARBG.mp4</link>
    <thumbnail>http://10.1.1.1/data/English%20Movies%20%281080p%29/%282011%29%201080p/Jane%20Eyre%20%282011%29%201080p/a_AL_.jpg</thumbnail>
    <fanart>http://10.1.1.1/data/English%20Movies%20%281080p%29/%282011%29%201080p/Jane%20Eyre%20%282011%29%201080p/a_AL_.jpg</fanart>
  </movie>
  <movie>
    <title>Johnny English Reborn (2011)</title>
    <link>http://10.1.1.1/data/English%20Movies%20%281080p%29/%282011%29%201080p/Johnny%20English%20Reborn%20%282011%29%201080p/Johnny%20English%20Reborn%20%282011%29%201080p%20BluRay%20x265%20HEVC%2010bit%20AAC%205.1-shadow.mkv</link>
    <thumbnail>http://10.1.1.1/data/English%20Movies%20%281080p%29/%282011%29%201080p/Johnny%20English%20Reborn%20%282011%29%201080p/a_AL_.jpg</thumbnail>
    <fanart>http://10.1.1.1/data/English%20Movies%20%281080p%29/%282011%29%201080p/Johnny%20English%20Reborn%20%282011%29%201080p/a_AL_.jpg</fanart>
  </movie>
  <movie>
    <title>Just Go with It (2011)</title>
    <link>http://10.1.1.1/data/English%20Movies%20%281080p%29/%282011%29%201080p/Just%20Go%20with%20It%20%282011%29%201080p/Just.Go.With.It.2011.1080p.BluRay.H264.AAC-RARBG.mp4</link>
    <thumbnail>http://10.1.1.1/data/English%20Movies%20%281080p%29/%282011%29%201080p/Just%20Go%20with%20It%20%282011%29%201080p/a_AL_.jpg</thumbnail>
    <fanart>http://10.1.1.1/data/English%20Movies%20%281080p%29/%282011%29%201080p/Just%20Go%20with%20It%20%282011%29%201080p/a_AL_.jpg</fanart>
  </movie>
  <movie>
    <title>Just Go with It (2011)</title>
    <link>http://10.1.1.1/data/English%20Movies%20%281080p%29/%282011%29%201080p/Just%20Go%20with%20It%20%282011%29%201080p%20%5BDual%20Audio%5D/Just%20Go%20with%20It%20%282011%29%201080p%20BluRay%20x265%20HEVC%20ESub%20%5BDual%20Audio%5D%5BHindi%202.0%2BEnglish%205.1%5D%20-mkvC.mkv</link>
    <thumbnail>http://10.1.1.1/data/English%20Movies%20%281080p%29/%282011%29%201080p/Just%20Go%20with%20It%20%282011%29%201080p%20%5BDual%20Audio%5D/a_AL_.jpg</thumbnail>
    <fanart>http://10.1.1.1/data/English%20Movies%20%281080p%29/%282011%29%201080p/Just%20Go%20with%20It%20%282011%29%201080p%20%5BDual%20Audio%5D/a_AL_.jpg</fanart>
  </movie>
  <movie>
    <title>Killer Elite (2011)</title>
    <link>http://10.1.1.1/data/English%20Movies%20%281080p%29/%282011%29%201080p/Killer%20Elite%20%282011%29%201080p/Killer%20Elite%20%282011%29%201080p%20BluRay%20x265%20HEVC%2010bit%205.1%20MSubs-pav69.mkv</link>
    <thumbnail>http://10.1.1.1/data/English%20Movies%20%281080p%29/%282011%29%201080p/Killer%20Elite%20%282011%29%201080p/a_AL_.jpg</thumbnail>
    <fanart>http://10.1.1.1/data/English%20Movies%20%281080p%29/%282011%29%201080p/Killer%20Elite%20%282011%29%201080p/a_AL_.jpg</fanart>
  </movie>
  <movie>
    <title>Killer Joe (2011)</title>
    <link>http://10.1.1.1/data/English%20Movies%20%281080p%29/%282011%29%201080p/Killer%20Joe%20%282011%29%201080p%20%5BDual%20Audio%5D/Killer%20Joe%20%282011%29%20DC%201080p%20BluRay%20x265%20HEVC%20ESub%20%5BDual%20Audio%5D%5BHindi%202.0%2BEnglish%205.1%5D%20-KmHD.mkv</link>
    <thumbnail>http://10.1.1.1/data/English%20Movies%20%281080p%29/%282011%29%201080p/Killer%20Joe%20%282011%29%201080p%20%5BDual%20Audio%5D/a_AL_.jpg</thumbnail>
    <fanart>http://10.1.1.1/data/English%20Movies%20%281080p%29/%282011%29%201080p/Killer%20Joe%20%282011%29%201080p%20%5BDual%20Audio%5D/a_AL_.jpg</fanart>
  </movie>
  <movie>
    <title>Larry Crowne (2011)</title>
    <link>http://10.1.1.1/data/English%20Movies%20%281080p%29/%282011%29%201080p/Larry%20Crowne%20%282011%29%201080p/Larry.Crowne.2011.1080p.BluRay.H264.AAC-RARBG.mp4</link>
    <thumbnail>http://10.1.1.1/data/English%20Movies%20%281080p%29/%282011%29%201080p/Larry%20Crowne%20%282011%29%201080p/a_AL_.jpg</thumbnail>
    <fanart>http://10.1.1.1/data/English%20Movies%20%281080p%29/%282011%29%201080p/Larry%20Crowne%20%282011%29%201080p/a_AL_.jpg</fanart>
  </movie>
  <movie>
    <title>Limitless (2011)</title>
    <link>http://10.1.1.1/data/English%20Movies%20%281080p%29/%282011%29%201080p/Limitless%20%282011%29%201080p/Limitless%20%282011%29%20Unrated%20Extended%201080p%20BluRay%20x265%20HEVC%2010bit%20AAC%205.1-afm72.mkv</link>
    <thumbnail>http://10.1.1.1/data/English%20Movies%20%281080p%29/%282011%29%201080p/Limitless%20%282011%29%201080p/a_AL_.jpg</thumbnail>
    <fanart>http://10.1.1.1/data/English%20Movies%20%281080p%29/%282011%29%201080p/Limitless%20%282011%29%201080p/a_AL_.jpg</fanart>
  </movie>
  <movie>
    <title>Machine Gun Preacher (2011)</title>
    <link>http://10.1.1.1/data/English%20Movies%20%281080p%29/%282011%29%201080p/Machine%20Gun%20Preacher%20%282011%29%201080p%20%5BDual%20Audio%5D/Machine%20Gun%20Preacher%20%282011%29%201080p%20BluRay%20x265%20HEVC%20ESub%20%5BDual%20Audio%5D%5BHindi%202.0%2BEnglish%205.1%5D%20-mkvC.mkv</link>
    <thumbnail>http://10.1.1.1/data/English%20Movies%20%281080p%29/%282011%29%201080p/Machine%20Gun%20Preacher%20%282011%29%201080p%20%5BDual%20Audio%5D/a_AL_.jpg</thumbnail>
    <fanart>http://10.1.1.1/data/English%20Movies%20%281080p%29/%282011%29%201080p/Machine%20Gun%20Preacher%20%282011%29%201080p%20%5BDual%20Audio%5D/a_AL_.jpg</fanart>
  </movie>
  <movie>
    <title>Melancholia (2011)</title>
    <link>http://10.1.1.1/data/English%20Movies%20%281080p%29/%282011%29%201080p/Melancholia%20%282011%29%201080p/Melancholia%20%282011%29%201080p%20BluRay%20x265%20HEVC%2010bit%20AAC%205.1%20MSubs-Tigole.mkv</link>
    <thumbnail>http://10.1.1.1/data/English%20Movies%20%281080p%29/%282011%29%201080p/Melancholia%20%282011%29%201080p/a_AL_.jpg</thumbnail>
    <fanart>http://10.1.1.1/data/English%20Movies%20%281080p%29/%282011%29%201080p/Melancholia%20%282011%29%201080p/a_AL_.jpg</fanart>
  </movie>
  <movie>
    <title>Midnight in Paris (2011)</title>
    <link>http://10.1.1.1/data/English%20Movies%20%281080p%29/%282011%29%201080p/Midnight%20in%20Paris%20%282011%29%201080p/Midnight.in.Paris.2011.1080p.BluRay.H264.AAC-RARBG.mp4</link>
    <thumbnail>http://10.1.1.1/data/English%20Movies%20%281080p%29/%282011%29%201080p/Midnight%20in%20Paris%20%282011%29%201080p/a_AL_.jpg</thumbnail>
    <fanart>http://10.1.1.1/data/English%20Movies%20%281080p%29/%282011%29%201080p/Midnight%20in%20Paris%20%282011%29%201080p/a_AL_.jpg</fanart>
  </movie>
  <movie>
    <title>Mission-Impossible - Ghost Protocol (2011)</title>
    <link>http://10.1.1.1/data/English%20Movies%20%281080p%29/%282011%29%201080p/Mission-Impossible%20-%20Ghost%20Protocol%20%282011%29%201080p/Mission-Impossible%20-%20Ghost%20Protocol%20%282011%29%201080p%20BluRay%20x265%20HEVC%207.1%20MSubs-Tigole.mkv</link>
    <thumbnail>http://10.1.1.1/data/English%20Movies%20%281080p%29/%282011%29%201080p/Mission-Impossible%20-%20Ghost%20Protocol%20%282011%29%201080p/a_AL_.jpg</thumbnail>
    <fanart>http://10.1.1.1/data/English%20Movies%20%281080p%29/%282011%29%201080p/Mission-Impossible%20-%20Ghost%20Protocol%20%282011%29%201080p/a_AL_.jpg</fanart>
  </movie>
  <movie>
    <title>Moneyball (2011)</title>
    <link>http://10.1.1.1/data/English%20Movies%20%281080p%29/%282011%29%201080p/Moneyball%20%282011%29%201080p/Moneyball%20%282011%29%20RM4K%201080p%20BluRay%20x265%20HEVC%2010bit%20AAC%205.1%20MSubs-Tigole.mkv</link>
    <thumbnail>http://10.1.1.1/data/English%20Movies%20%281080p%29/%282011%29%201080p/Moneyball%20%282011%29%201080p/a_AL_.jpg</thumbnail>
    <fanart>http://10.1.1.1/data/English%20Movies%20%281080p%29/%282011%29%201080p/Moneyball%20%282011%29%201080p/a_AL_.jpg</fanart>
  </movie>
  <movie>
    <title>Mr. Popper's Penguins (2011)</title>
    <link>http://10.1.1.1/data/English%20Movies%20%281080p%29/%282011%29%201080p/Mr.%20Popper%27s%20Penguins%20%282011%29%201080p/Mr.%20Popper%27s%20Penguins%20%282011%29%201080p%20BluRay%20x265%20HEVC%2010bit%20AAC%205.1%20MSubs-Tigole.mkv</link>
    <thumbnail>http://10.1.1.1/data/English%20Movies%20%281080p%29/%282011%29%201080p/Mr.%20Popper%27s%20Penguins%20%282011%29%201080p/a_AL_.jpg</thumbnail>
    <fanart>http://10.1.1.1/data/English%20Movies%20%281080p%29/%282011%29%201080p/Mr.%20Popper%27s%20Penguins%20%282011%29%201080p/a_AL_.jpg</fanart>
  </movie>
  <movie>
    <title>One Day (2011)</title>
    <link>http://10.1.1.1/data/English%20Movies%20%281080p%29/%282011%29%201080p/One%20Day%20%282011%29%201080p/One.Day.2011.1080p.BluRay.H264.AAC-RARBG.mp4</link>
    <thumbnail>http://10.1.1.1/data/English%20Movies%20%281080p%29/%282011%29%201080p/One%20Day%20%282011%29%201080p/a_AL_.jpg</thumbnail>
    <fanart>http://10.1.1.1/data/English%20Movies%20%281080p%29/%282011%29%201080p/One%20Day%20%282011%29%201080p/a_AL_.jpg</fanart>
  </movie>
  <movie>
    <title>One Day (2011)</title>
    <link>http://10.1.1.1/data/English%20Movies%20%281080p%29/%282011%29%201080p/One%20Day%20%282011%29%201080p%20%5BDual%20Audio%5D/One%20Day%20%282011%29%201080p%20BluRay%20x265%20HEVC%20ESub%20%5BDual%20Audio%5D%5BHindi%205.1%2BEnglish%205.1%5D%20-mkvC.mkv</link>
    <thumbnail>http://10.1.1.1/data/English%20Movies%20%281080p%29/%282011%29%201080p/One%20Day%20%282011%29%201080p%20%5BDual%20Audio%5D/a_AL_.jpg</thumbnail>
    <fanart>http://10.1.1.1/data/English%20Movies%20%281080p%29/%282011%29%201080p/One%20Day%20%282011%29%201080p%20%5BDual%20Audio%5D/a_AL_.jpg</fanart>
  </movie>
  <movie>
    <title>Page Eight (2011)</title>
    <link>http://10.1.1.1/data/English%20Movies%20%281080p%29/%282011%29%201080p/Page%20Eight%20%282011%29%201080p/Page.Eight.2011.1080p.BluRay.x264.anoXmous_.mp4</link>
    <thumbnail>http://10.1.1.1/data/English%20Movies%20%281080p%29/%282011%29%201080p/Page%20Eight%20%282011%29%201080p/anal.jpg</thumbnail>
    <fanart>http://10.1.1.1/data/English%20Movies%20%281080p%29/%282011%29%201080p/Page%20Eight%20%282011%29%201080p/anal.jpg</fanart>
  </movie>
  <movie>
    <title>Paul (2011)</title>
    <link>http://10.1.1.1/data/English%20Movies%20%281080p%29/%282011%29%201080p/Paul%20%282011%29%201080p%20%5BDual%20Audio%5D/Paul%20%282011%29%20EXTENDED%201080p%20BluRay%20x265%20HEVC%20ESub%20%5BDual%20Audio%5D%5BHindi%205.1%2BEnglish%205.1%5D%20-MsHeist.mkv</link>
    <thumbnail>http://10.1.1.1/data/English%20Movies%20%281080p%29/%282011%29%201080p/Paul%20%282011%29%201080p%20%5BDual%20Audio%5D/a_AL_.jpg</thumbnail>
    <fanart>http://10.1.1.1/data/English%20Movies%20%281080p%29/%282011%29%201080p/Paul%20%282011%29%201080p%20%5BDual%20Audio%5D/a_AL_.jpg</fanart>
  </movie>
  <movie>
    <title>Pirates of the Caribbean-On Stranger Tides (2011)</title>
    <link>http://10.1.1.1/data/English%20Movies%20%281080p%29/%282011%29%201080p/Pirates%20of%20the%20Caribbean-On%20Stranger%20Tides%20%282011%29%201080p%20%5BDual%20Audio%5D/Pirates%20of%20the%20Caribbean%20On%20Stranger%20Tides%20%282011%29%201080p%20BluRay%20x265%20HEVC%20ESub%20%5BDual%20Audio%5D%5BHindi%205.1%2BEnglish%205.1%5D%20-MsHeist.mkv</link>
    <thumbnail>http://10.1.1.1/data/English%20Movies%20%281080p%29/%282011%29%201080p/Pirates%20of%20the%20Caribbean-On%20Stranger%20Tides%20%282011%29%201080p%20%5BDual%20Audio%5D/a_AL_.jpg</thumbnail>
    <fanart>http://10.1.1.1/data/English%20Movies%20%281080p%29/%282011%29%201080p/Pirates%20of%20the%20Caribbean-On%20Stranger%20Tides%20%282011%29%201080p%20%5BDual%20Audio%5D/a_AL_.jpg</fanart>
  </movie>
  <movie>
    <title>Priest (2011)</title>
    <link>http://10.1.1.1/data/English%20Movies%20%281080p%29/%282011%29%201080p/Priest%20%282011%29%201080p/Priest%20%282011%29%201080p%20BluRay%20x265%20HEVC%2010bit%20AAC%205.1%20MSubs-Tigole.mkv</link>
    <thumbnail>http://10.1.1.1/data/English%20Movies%20%281080p%29/%282011%29%201080p/Priest%20%282011%29%201080p/a_AL_.jpg</thumbnail>
    <fanart>http://10.1.1.1/data/English%20Movies%20%281080p%29/%282011%29%201080p/Priest%20%282011%29%201080p/a_AL_.jpg</fanart>
  </movie>
  <movie>
    <title>Real Steel (2011)</title>
    <link>http://10.1.1.1/data/English%20Movies%20%281080p%29/%282011%29%201080p/Real%20Steel%20%282011%29%201080p/Real%20Steel%20%282011%29%201080p%20BluRay%20x265%20HEVC%2010bit%20AAC%205.1%20ESub-Vyndros.mkv</link>
    <thumbnail>http://10.1.1.1/data/English%20Movies%20%281080p%29/%282011%29%201080p/Real%20Steel%20%282011%29%201080p/a_AL_.jpg</thumbnail>
    <fanart>http://10.1.1.1/data/English%20Movies%20%281080p%29/%282011%29%201080p/Real%20Steel%20%282011%29%201080p/a_AL_.jpg</fanart>
  </movie>
  <movie>
    <title>Red Riding Hood (2011)</title>
    <link>http://10.1.1.1/data/English%20Movies%20%281080p%29/%282011%29%201080p/Red%20Riding%20Hood%20%282011%29%201080p/Red.Riding.Hood.2011.1080p.BluRay.H264.AAC-RARBG.mp4</link>
    <thumbnail>http://10.1.1.1/data/English%20Movies%20%281080p%29/%282011%29%201080p/Red%20Riding%20Hood%20%282011%29%201080p/a_AL_.jpg</thumbnail>
    <fanart>http://10.1.1.1/data/English%20Movies%20%281080p%29/%282011%29%201080p/Red%20Riding%20Hood%20%282011%29%201080p/a_AL_.jpg</fanart>
  </movie>
  <movie>
    <title>Rise of the Planet of the Apes (2011)</title>
    <link>http://10.1.1.1/data/English%20Movies%20%281080p%29/%282011%29%201080p/Rise%20of%20the%20Planet%20of%20the%20Apes%20%282011%29%201080p/Rise%20of%20the%20Planet%20of%20the%20Apes%20%282011%29%201080p%20BluRay%20x265%20HEVC%205.1%20MSubs-Tigole.mkv</link>
    <thumbnail>http://10.1.1.1/data/English%20Movies%20%281080p%29/%282011%29%201080p/Rise%20of%20the%20Planet%20of%20the%20Apes%20%282011%29%201080p/a_AL_.jpg</thumbnail>
    <fanart>http://10.1.1.1/data/English%20Movies%20%281080p%29/%282011%29%201080p/Rise%20of%20the%20Planet%20of%20the%20Apes%20%282011%29%201080p/a_AL_.jpg</fanart>
  </movie>
  <movie>
    <title>Rise of the Planet of the Apes (2011)</title>
    <link>http://10.1.1.1/data/English%20Movies%20%281080p%29/%282011%29%201080p/Rise%20of%20the%20Planet%20of%20the%20Apes%20%282011%29%201080p%20%5BDual%20Audio%5D/Rise%20of%20the%20Planet%20of%20the%20Apes%20%282011%29%201080p%20BluRay%20x265%20HEVC%20ESub%20%5BDual%20Audio%5D%5BHindi%205.1%2BEnglish%205.1%5D%20-mkvC.mkv</link>
    <thumbnail>http://10.1.1.1/data/English%20Movies%20%281080p%29/%282011%29%201080p/Rise%20of%20the%20Planet%20of%20the%20Apes%20%282011%29%201080p%20%5BDual%20Audio%5D/a_AL_.jpg</thumbnail>
    <fanart>http://10.1.1.1/data/English%20Movies%20%281080p%29/%282011%29%201080p/Rise%20of%20the%20Planet%20of%20the%20Apes%20%282011%29%201080p%20%5BDual%20Audio%5D/a_AL_.jpg</fanart>
  </movie>
  <movie>
    <title>Sanctum (2011)</title>
    <link>http://10.1.1.1/data/English%20Movies%20%281080p%29/%282011%29%201080p/Sanctum%20%282011%29%201080p/Sanctum.2011.1080p.BluRay.H264.AAC-RARBG.mp4</link>
    <thumbnail>http://10.1.1.1/data/English%20Movies%20%281080p%29/%282011%29%201080p/Sanctum%20%282011%29%201080p/a_AL_.jpg</thumbnail>
    <fanart>http://10.1.1.1/data/English%20Movies%20%281080p%29/%282011%29%201080p/Sanctum%20%282011%29%201080p/a_AL_.jpg</fanart>
  </movie>
  <movie>
    <title>Scream 4 (2011)</title>
    <link>http://10.1.1.1/data/English%20Movies%20%281080p%29/%282011%29%201080p/Scream%204%20%282011%29%201080p/Scream%204%20%282011%29%201080p%20BluRay%20x265%20HEVC%2010bit%20AAC%205.1%20MSubs-Tigole.mkv</link>
    <thumbnail>http://10.1.1.1/data/English%20Movies%20%281080p%29/%282011%29%201080p/Scream%204%20%282011%29%201080p/a_AL_.jpg</thumbnail>
    <fanart>http://10.1.1.1/data/English%20Movies%20%281080p%29/%282011%29%201080p/Scream%204%20%282011%29%201080p/a_AL_.jpg</fanart>
  </movie>
  <movie>
    <title>Season of the Witch (2011)</title>
    <link>http://10.1.1.1/data/English%20Movies%20%281080p%29/%282011%29%201080p/Season%20of%20the%20Witch%20%282011%29%201080p/Season.of.the.Witch.2011.1080p.BluRay.H264.AAC-RARBG.mp4</link>
    <thumbnail>http://10.1.1.1/data/English%20Movies%20%281080p%29/%282011%29%201080p/Season%20of%20the%20Witch%20%282011%29%201080p/a_AL_.jpg</thumbnail>
    <fanart>http://10.1.1.1/data/English%20Movies%20%281080p%29/%282011%29%201080p/Season%20of%20the%20Witch%20%282011%29%201080p/a_AL_.jpg</fanart>
  </movie>
  <movie>
    <title>Sherlock Holmes-A Game of Shadows (2011)</title>
    <link>http://10.1.1.1/data/English%20Movies%20%281080p%29/%282011%29%201080p/Sherlock%20Holmes-A%20Game%20of%20Shadows%20%282011%29%201080p/Sherlock%20Holmes-A%20Game%20of%20Shadows%20%282011%29%201080p%20BluRay%20x265%20HEVC%205.1%20ESub-Tigole.mkv</link>
    <thumbnail>http://10.1.1.1/data/English%20Movies%20%281080p%29/%282011%29%201080p/Sherlock%20Holmes-A%20Game%20of%20Shadows%20%282011%29%201080p/a_AL_.jpg</thumbnail>
    <fanart>http://10.1.1.1/data/English%20Movies%20%281080p%29/%282011%29%201080p/Sherlock%20Holmes-A%20Game%20of%20Shadows%20%282011%29%201080p/a_AL_.jpg</fanart>
  </movie>
  <movie>
    <title>Source Code (2011)</title>
    <link>http://10.1.1.1/data/English%20Movies%20%281080p%29/%282011%29%201080p/Source%20Code%20%282011%29%201080p/Source%20Code%20%282011%29%201080p%20BluRay%20x265%20HEVC%2010bit%20AAC%205.1%20MSubs-Silence.mkv</link>
    <thumbnail>http://10.1.1.1/data/English%20Movies%20%281080p%29/%282011%29%201080p/Source%20Code%20%282011%29%201080p/a_AL_.jpg</thumbnail>
    <fanart>http://10.1.1.1/data/English%20Movies%20%281080p%29/%282011%29%201080p/Source%20Code%20%282011%29%201080p/a_AL_.jpg</fanart>
  </movie>
  <movie>
    <title>Sucker Punch (2011)</title>
    <link>http://10.1.1.1/data/English%20Movies%20%281080p%29/%282011%29%201080p/Sucker%20Punch%20%282011%29%201080p/Sucker.Punch.2011.Extended.Cut.1080p.BluRay.H264.AAC-RARBG.mp4</link>
    <thumbnail>http://10.1.1.1/data/English%20Movies%20%281080p%29/%282011%29%201080p/Sucker%20Punch%20%282011%29%201080p/a_AL_.jpg</thumbnail>
    <fanart>http://10.1.1.1/data/English%20Movies%20%281080p%29/%282011%29%201080p/Sucker%20Punch%20%282011%29%201080p/a_AL_.jpg</fanart>
  </movie>
  <movie>
    <title>Super 8 (2011)</title>
    <link>http://10.1.1.1/data/English%20Movies%20%281080p%29/%282011%29%201080p/Super%208%20%282011%29%201080p/Super%208%20%282011%29%201080p%20BluRay%20x265%20HEVC%2010bit%20AAC%207.1%20MSubs-Tigole.mkv</link>
    <thumbnail>http://10.1.1.1/data/English%20Movies%20%281080p%29/%282011%29%201080p/Super%208%20%282011%29%201080p/a_AL_.jpg</thumbnail>
    <fanart>http://10.1.1.1/data/English%20Movies%20%281080p%29/%282011%29%201080p/Super%208%20%282011%29%201080p/a_AL_.jpg</fanart>
  </movie>
  <movie>
    <title>Take Me Home Tonight (2011)</title>
    <link>http://10.1.1.1/data/English%20Movies%20%281080p%29/%282011%29%201080p/Take%20Me%20Home%20Tonight%20%282011%29%201080p%20%5BDual%20Audio%5D/Take%20Me%20Home%20Tonight%20%282011%29%201080p%20BluRay%20x265%20HEVC%20ESub%20%5BDual%20Audio%5D%5BHindi%205.1%2BEnglish%205.1%5D%20-mkvC.mkv</link>
    <thumbnail>http://10.1.1.1/data/English%20Movies%20%281080p%29/%282011%29%201080p/Take%20Me%20Home%20Tonight%20%282011%29%201080p%20%5BDual%20Audio%5D/a_AL_.jpg</thumbnail>
    <fanart>http://10.1.1.1/data/English%20Movies%20%281080p%29/%282011%29%201080p/Take%20Me%20Home%20Tonight%20%282011%29%201080p%20%5BDual%20Audio%5D/a_AL_.jpg</fanart>
  </movie>
  <movie>
    <title>Take Shelter (2011)</title>
    <link>http://10.1.1.1/data/English%20Movies%20%281080p%29/%282011%29%201080p/Take%20Shelter%20%282011%29%201080p/Take%20Shelter%20%282011%29%201080p%20BluRay%20x265%20HEVC%2010bit%20AAC%205.1%20MSubs-Tigole.mkv</link>
    <thumbnail>http://10.1.1.1/data/English%20Movies%20%281080p%29/%282011%29%201080p/Take%20Shelter%20%282011%29%201080p/a_AL_.jpg</thumbnail>
    <fanart>http://10.1.1.1/data/English%20Movies%20%281080p%29/%282011%29%201080p/Take%20Shelter%20%282011%29%201080p/a_AL_.jpg</fanart>
  </movie>
  <movie>
    <title>The Adjustment Bureau (2011)</title>
    <link>http://10.1.1.1/data/English%20Movies%20%281080p%29/%282011%29%201080p/The%20Adjustment%20Bureau%20%282011%29%201080p/The%20Adjustment%20Bureau%20%282011%29%201080p%20BluRay%20x265%20HEVC%20AC3%205.1-SharpysWord.mkv</link>
    <thumbnail>http://10.1.1.1/data/English%20Movies%20%281080p%29/%282011%29%201080p/The%20Adjustment%20Bureau%20%282011%29%201080p/a_AL_.jpg</thumbnail>
    <fanart>http://10.1.1.1/data/English%20Movies%20%281080p%29/%282011%29%201080p/The%20Adjustment%20Bureau%20%282011%29%201080p/a_AL_.jpg</fanart>
  </movie>
  <movie>
    <title>The Artist (2011)</title>
    <link>http://10.1.1.1/data/English%20Movies%20%281080p%29/%282011%29%201080p/The%20Artist%20%282011%29%201080p/The%20Artist%20%282011%29%201080p%20BluRay%20x265%20HEVC%2010bit%20AAC%205.1-Tigole.mkv</link>
    <thumbnail>http://10.1.1.1/data/English%20Movies%20%281080p%29/%282011%29%201080p/The%20Artist%20%282011%29%201080p/a_AL_.jpg</thumbnail>
    <fanart>http://10.1.1.1/data/English%20Movies%20%281080p%29/%282011%29%201080p/The%20Artist%20%282011%29%201080p/a_AL_.jpg</fanart>
  </movie>
  <movie>
    <title>The Beaver (2011)</title>
    <link>http://10.1.1.1/data/English%20Movies%20%281080p%29/%282011%29%201080p/The%20Beaver%20%282011%29%201080p/The.Beaver.2011.1080p.BluRay.H264.AAC-RARBG.mp4</link>
    <thumbnail>http://10.1.1.1/data/English%20Movies%20%281080p%29/%282011%29%201080p/The%20Beaver%20%282011%29%201080p/a_AL_.jpg</thumbnail>
    <fanart>http://10.1.1.1/data/English%20Movies%20%281080p%29/%282011%29%201080p/The%20Beaver%20%282011%29%201080p/a_AL_.jpg</fanart>
  </movie>
  <movie>
    <title>The Darkest Hour (2011)</title>
    <link>http://10.1.1.1/data/English%20Movies%20%281080p%29/%282011%29%201080p/The%20Darkest%20Hour%20%282011%29%201080p%20%5BDual%20Audio%5D/The%20Darkest%20Hour%20%282011%29%201080p%20BluRay%20x265%20HEVC%20ESub%20%5BDual%20Audio%5D%5BHindi%205.1%2BEnglish%205.1%5D%20-mkvC.mkv</link>
    <thumbnail>http://10.1.1.1/data/English%20Movies%20%281080p%29/%282011%29%201080p/The%20Darkest%20Hour%20%282011%29%201080p%20%5BDual%20Audio%5D/a_AL_.jpg</thumbnail>
    <fanart>http://10.1.1.1/data/English%20Movies%20%281080p%29/%282011%29%201080p/The%20Darkest%20Hour%20%282011%29%201080p%20%5BDual%20Audio%5D/a_AL_.jpg</fanart>
  </movie>
  <movie>
    <title>The Descendants (2011)</title>
    <link>http://10.1.1.1/data/English%20Movies%20%281080p%29/%282011%29%201080p/The%20Descendants%20%282011%29%201080p/The.Descendants.2011.1080p.BluRay.H264.AAC-RARBG.mp4</link>
    <thumbnail>http://10.1.1.1/data/English%20Movies%20%281080p%29/%282011%29%201080p/The%20Descendants%20%282011%29%201080p/a_AL_.jpg</thumbnail>
    <fanart>http://10.1.1.1/data/English%20Movies%20%281080p%29/%282011%29%201080p/The%20Descendants%20%282011%29%201080p/a_AL_.jpg</fanart>
  </movie>
  <movie>
    <title>The Devil's Double (2011)</title>
    <link>http://10.1.1.1/data/English%20Movies%20%281080p%29/%282011%29%201080p/The%20Devil%27s%20Double%20%282011%29%201080p/The%20Devil%27s%20Double%20%282011%29%201080p%20BluRay%20x265%20HEVC%2010bit%20AAC%207.1%20MSubs-Tigole.mkv</link>
    <thumbnail>http://10.1.1.1/data/English%20Movies%20%281080p%29/%282011%29%201080p/The%20Devil%27s%20Double%20%282011%29%201080p/a_AL_.jpg</thumbnail>
    <fanart>http://10.1.1.1/data/English%20Movies%20%281080p%29/%282011%29%201080p/The%20Devil%27s%20Double%20%282011%29%201080p/a_AL_.jpg</fanart>
  </movie>
  <movie>
    <title>The Eagle (2011)</title>
    <link>http://10.1.1.1/data/English%20Movies%20%281080p%29/%282011%29%201080p/The%20Eagle%20%282011%29%201080p%20%5BDual%20Audio%5D/The%20Eagle%20%282011%29%201080p%20BluRay%20x265%20HEVC%20ESub%20%5BDual%20Audio%5D%5BHindi%205.1%2BEnglish%205.1%5D%20-mkvC.mkv</link>
    <thumbnail>http://10.1.1.1/data/English%20Movies%20%281080p%29/%282011%29%201080p/The%20Eagle%20%282011%29%201080p%20%5BDual%20Audio%5D/a_AL_.jpg</thumbnail>
    <fanart>http://10.1.1.1/data/English%20Movies%20%281080p%29/%282011%29%201080p/The%20Eagle%20%282011%29%201080p%20%5BDual%20Audio%5D/a_AL_.jpg</fanart>
  </movie>
  <movie>
    <title>The Girl with the Dragon Tattoo (2011)</title>
    <link>http://10.1.1.1/data/English%20Movies%20%281080p%29/%282011%29%201080p/The%20Girl%20with%20the%20Dragon%20Tattoo%20%282011%29%201080p/The%20Girl%20with%20the%20Dragon%20Tattoo%20%282011%29%201080p%20BluRay%20x265%20HEVC%20AAC%205.1%20MSubs-Tigole.mkv</link>
    <thumbnail>http://10.1.1.1/data/English%20Movies%20%281080p%29/%282011%29%201080p/The%20Girl%20with%20the%20Dragon%20Tattoo%20%282011%29%201080p/a_AL_.jpg</thumbnail>
    <fanart>http://10.1.1.1/data/English%20Movies%20%281080p%29/%282011%29%201080p/The%20Girl%20with%20the%20Dragon%20Tattoo%20%282011%29%201080p/a_AL_.jpg</fanart>
  </movie>
  <movie>
    <title>The Green Hornet (2011)</title>
    <link>http://10.1.1.1/data/English%20Movies%20%281080p%29/%282011%29%201080p/The%20Green%20Hornet%20%282011%29%201080p/The.Green.Hornet.2011.1080p.BluRay.H264.AAC-RARBG.mp4</link>
    <thumbnail>http://10.1.1.1/data/English%20Movies%20%281080p%29/%282011%29%201080p/The%20Green%20Hornet%20%282011%29%201080p/a_AL_.jpg</thumbnail>
    <fanart>http://10.1.1.1/data/English%20Movies%20%281080p%29/%282011%29%201080p/The%20Green%20Hornet%20%282011%29%201080p/a_AL_.jpg</fanart>
  </movie>
  <movie>
    <title>The Grey (2011)</title>
    <link>http://10.1.1.1/data/English%20Movies%20%281080p%29/%282011%29%201080p/The%20Grey%20%282011%29%201080p/The.Grey.2011.1080p.BluRay.x264.x264.YIFY.mp4</link>
    <thumbnail>http://10.1.1.1/data/English%20Movies%20%281080p%29/%282011%29%201080p/The%20Grey%20%282011%29%201080p/a_AL_.jpg</thumbnail>
    <fanart>http://10.1.1.1/data/English%20Movies%20%281080p%29/%282011%29%201080p/The%20Grey%20%282011%29%201080p/a_AL_.jpg</fanart>
  </movie>
  <movie>
    <title>The Hangover Part II (2011)</title>
    <link>http://10.1.1.1/data/English%20Movies%20%281080p%29/%282011%29%201080p/The%20Hangover%20Part%20II%20%282011%29%201080p/The%20Hangover%20Part%20II%20%282011%29%201080p%20BluRay%20x265%20HEVC%2010bit%20DD5.1%20ESub-shadow.mkv</link>
    <thumbnail>http://10.1.1.1/data/English%20Movies%20%281080p%29/%282011%29%201080p/The%20Hangover%20Part%20II%20%282011%29%201080p/a_AL_.jpg</thumbnail>
    <fanart>http://10.1.1.1/data/English%20Movies%20%281080p%29/%282011%29%201080p/The%20Hangover%20Part%20II%20%282011%29%201080p/a_AL_.jpg</fanart>
  </movie>
  <movie>
    <title>The Help (2011)</title>
    <link>http://10.1.1.1/data/English%20Movies%20%281080p%29/%282011%29%201080p/The%20Help%20%282011%29%201080p/The%20Help%20%282011%29%201080p%20BluRay%20x265%20HEVC%2010bit%20AAC%205.1%20MSubs-Tigole.mkv</link>
    <thumbnail>http://10.1.1.1/data/English%20Movies%20%281080p%29/%282011%29%201080p/The%20Help%20%282011%29%201080p/a_AL_.jpg</thumbnail>
    <fanart>http://10.1.1.1/data/English%20Movies%20%281080p%29/%282011%29%201080p/The%20Help%20%282011%29%201080p/a_AL_.jpg</fanart>
  </movie>
  <movie>
    <title>The Hunter (2011)</title>
    <link>http://10.1.1.1/data/English%20Movies%20%281080p%29/%282011%29%201080p/The%20Hunter%20%282011%29%201080p/The.Hunter.2011.1080p.BluRay.H264.AAC-RARBG.mp4</link>
    <thumbnail>http://10.1.1.1/data/English%20Movies%20%281080p%29/%282011%29%201080p/The%20Hunter%20%282011%29%201080p/a_AL_.jpg</thumbnail>
    <fanart>http://10.1.1.1/data/English%20Movies%20%281080p%29/%282011%29%201080p/The%20Hunter%20%282011%29%201080p/a_AL_.jpg</fanart>
  </movie>
  <movie>
    <title>The Intouchables (2011)</title>
    <link>http://10.1.1.1/data/English%20Movies%20%281080p%29/%282011%29%201080p/The%20Intouchables%20%282011%29%201080p%20NF/The%20Intouchables%20%282011%29%201080p%20NF-WEB%20x264%20AAC%205.1%20ESub-mkvC.mkv</link>
    <thumbnail>http://10.1.1.1/data/English%20Movies%20%281080p%29/%282011%29%201080p/The%20Intouchables%20%282011%29%201080p%20NF/a_AL_.jpg</thumbnail>
    <fanart>http://10.1.1.1/data/English%20Movies%20%281080p%29/%282011%29%201080p/The%20Intouchables%20%282011%29%201080p%20NF/a_AL_.jpg</fanart>
  </movie>
  <movie>
    <title>The Lincoln Lawyer (2011)</title>
    <link>http://10.1.1.1/data/English%20Movies%20%281080p%29/%282011%29%201080p/The%20Lincoln%20Lawyer%20%282011%29%201080p/The%20Lincoln%20Lawyer%20%282011%29%201080p%20BluRay%20x265%20HEVC%2010bit%20AAC%207.1%20ESub-afm72.mkv</link>
    <thumbnail>http://10.1.1.1/data/English%20Movies%20%281080p%29/%282011%29%201080p/The%20Lincoln%20Lawyer%20%282011%29%201080p/a_AL_.jpg</thumbnail>
    <fanart>http://10.1.1.1/data/English%20Movies%20%281080p%29/%282011%29%201080p/The%20Lincoln%20Lawyer%20%282011%29%201080p/a_AL_.jpg</fanart>
  </movie>
  <movie>
    <title>The Mechanic (2011)</title>
    <link>http://10.1.1.1/data/English%20Movies%20%281080p%29/%282011%29%201080p/The%20Mechanic%20%282011%29%201080p/The.Mechanic.2011.1080p.BluRay.H264.AAC-RARBG.mp4</link>
    <thumbnail>http://10.1.1.1/data/English%20Movies%20%281080p%29/%282011%29%201080p/The%20Mechanic%20%282011%29%201080p/a_AL_.jpg</thumbnail>
    <fanart>http://10.1.1.1/data/English%20Movies%20%281080p%29/%282011%29%201080p/The%20Mechanic%20%282011%29%201080p/a_AL_.jpg</fanart>
  </movie>
  <movie>
    <title>The Rum Diary (2011)</title>
    <link>http://10.1.1.1/data/English%20Movies%20%281080p%29/%282011%29%201080p/The%20Rum%20Diary%20%282011%29%201080p/The%20Rum%20Diary%20%282011%29%201080p%20BluRay%20x265%20HEVC%2010bit%20AAC%205.1%20MSubs-Tigole.mkv</link>
    <thumbnail>http://10.1.1.1/data/English%20Movies%20%281080p%29/%282011%29%201080p/The%20Rum%20Diary%20%282011%29%201080p/a_AL_.jpg</thumbnail>
    <fanart>http://10.1.1.1/data/English%20Movies%20%281080p%29/%282011%29%201080p/The%20Rum%20Diary%20%282011%29%201080p/a_AL_.jpg</fanart>
  </movie>
  <movie>
    <title>The Thing (2011)</title>
    <link>http://10.1.1.1/data/English%20Movies%20%281080p%29/%282011%29%201080p/The%20Thing%20%282011%29%201080p/The%20Thing%20%282011%29%201080p%20BluRay%20x265%20HEVC.10bit%205.1%20ESub-pav69.mkv</link>
    <thumbnail>http://10.1.1.1/data/English%20Movies%20%281080p%29/%282011%29%201080p/The%20Thing%20%282011%29%201080p/a_AL_.jpg</thumbnail>
    <fanart>http://10.1.1.1/data/English%20Movies%20%281080p%29/%282011%29%201080p/The%20Thing%20%282011%29%201080p/a_AL_.jpg</fanart>
  </movie>
  <movie>
    <title>The Three Musketeers (2011)</title>
    <link>http://10.1.1.1/data/English%20Movies%20%281080p%29/%282011%29%201080p/The%20Three%20Musketeers%20%282011%29%201080p/The%20Three%20Musketeers%20%282011%29%201080p%20BluRay%20x265%20HEVC%2010bit%20AAC%205.1%20MSubs-Tigole.mkv</link>
    <thumbnail>http://10.1.1.1/data/English%20Movies%20%281080p%29/%282011%29%201080p/The%20Three%20Musketeers%20%282011%29%201080p/a_AL_.jpg</thumbnail>
    <fanart>http://10.1.1.1/data/English%20Movies%20%281080p%29/%282011%29%201080p/The%20Three%20Musketeers%20%282011%29%201080p/a_AL_.jpg</fanart>
  </movie>
  <movie>
    <title>The Tree of Life (2011)</title>
    <link>http://10.1.1.1/data/English%20Movies%20%281080p%29/%282011%29%201080p/The%20Tree%20of%20Life%20%282011%29%201080p/The.Tree.of.Life.2011.EXTENDED.CUT.1080p.BluRay.H264.AAC-RARBG.mp4</link>
    <thumbnail>http://10.1.1.1/data/English%20Movies%20%281080p%29/%282011%29%201080p/The%20Tree%20of%20Life%20%282011%29%201080p/a_AL_.jpg</thumbnail>
    <fanart>http://10.1.1.1/data/English%20Movies%20%281080p%29/%282011%29%201080p/The%20Tree%20of%20Life%20%282011%29%201080p/a_AL_.jpg</fanart>
  </movie>
  <movie>
    <title>The Twilight Saga-Breaking Dawn - Part 1 (2011)</title>
    <link>http://10.1.1.1/data/English%20Movies%20%281080p%29/%282011%29%201080p/The%20Twilight%20Saga-Breaking%20Dawn%20-%20Part%201%20%282011%29%201080p/The.Twilight.Saga.Breaking.Dawn.Part.1.2011.PROPER.1080p.BluRay.H264.AAC-RARBG.mp4</link>
    <thumbnail>http://10.1.1.1/data/English%20Movies%20%281080p%29/%282011%29%201080p/The%20Twilight%20Saga-Breaking%20Dawn%20-%20Part%201%20%282011%29%201080p/a_AL_.jpg</thumbnail>
    <fanart>http://10.1.1.1/data/English%20Movies%20%281080p%29/%282011%29%201080p/The%20Twilight%20Saga-Breaking%20Dawn%20-%20Part%201%20%282011%29%201080p/a_AL_.jpg</fanart>
  </movie>
  <movie>
    <title>Thor (2011)</title>
    <link>http://10.1.1.1/data/English%20Movies%20%281080p%29/%282011%29%201080p/Thor%20%282011%29%201080p/Thor%20%282011%29%201080p%20UHD%20BluRay%20x265%20HEVC%2010bit%205.1%20ESub-pav69.mkv</link>
    <thumbnail>http://10.1.1.1/data/English%20Movies%20%281080p%29/%282011%29%201080p/Thor%20%282011%29%201080p/a_AL_.jpg</thumbnail>
    <fanart>http://10.1.1.1/data/English%20Movies%20%281080p%29/%282011%29%201080p/Thor%20%282011%29%201080p/a_AL_.jpg</fanart>
  </movie>
  <movie>
    <title>Tinker Tailor Soldier Spy (2011)</title>
    <link>http://10.1.1.1/data/English%20Movies%20%281080p%29/%282011%29%201080p/Tinker%20Tailor%20Soldier%20Spy%20%282011%29%201080p/Tinker%20Tailor%20Soldier%20Spy%20%282011%29%201080p%20BluRay%20x265%20HEVC%2010bit%20AAC%205.1%20MSubs-Tigole.mkv</link>
    <thumbnail>http://10.1.1.1/data/English%20Movies%20%281080p%29/%282011%29%201080p/Tinker%20Tailor%20Soldier%20Spy%20%282011%29%201080p/a_AL_.jpg</thumbnail>
    <fanart>http://10.1.1.1/data/English%20Movies%20%281080p%29/%282011%29%201080p/Tinker%20Tailor%20Soldier%20Spy%20%282011%29%201080p/a_AL_.jpg</fanart>
  </movie>
  <movie>
    <title>Transformers-Dark of the Moon (2011)</title>
    <link>http://10.1.1.1/data/English%20Movies%20%281080p%29/%282011%29%201080p/Transformers-Dark%20of%20the%20Moon%20%282011%29%201080p/Transformers-Dark%20of%20the%20Moon%20%282011%29%201080p%20BluRay%20x265%20HEVC%20AAC%207.1%20MSubs-Tigole.mkv</link>
    <thumbnail>http://10.1.1.1/data/English%20Movies%20%281080p%29/%282011%29%201080p/Transformers-Dark%20of%20the%20Moon%20%282011%29%201080p/a_AL_.jpg</thumbnail>
    <fanart>http://10.1.1.1/data/English%20Movies%20%281080p%29/%282011%29%201080p/Transformers-Dark%20of%20the%20Moon%20%282011%29%201080p/a_AL_.jpg</fanart>
  </movie>
  <movie>
    <title>Unknown (2011)</title>
    <link>http://10.1.1.1/data/English%20Movies%20%281080p%29/%282011%29%201080p/Unknown%20%282011%29%201080p/Unknown.2011.1080p.BluRay.x265.HEVC.10bit.5.1.ESub-pav69.mkv</link>
    <thumbnail>http://10.1.1.1/data/English%20Movies%20%281080p%29/%282011%29%201080p/Unknown%20%282011%29%201080p/a_AL_.jpg</thumbnail>
    <fanart>http://10.1.1.1/data/English%20Movies%20%281080p%29/%282011%29%201080p/Unknown%20%282011%29%201080p/a_AL_.jpg</fanart>
  </movie>
  <movie>
    <title>War Horse (2011)</title>
    <link>http://10.1.1.1/data/English%20Movies%20%281080p%29/%282011%29%201080p/War%20Horse%20%282011%29%201080p/War%20Horse%20%282011%29%201080p%20BluRay%20x265%20HEVC%2010bit%20AAC%207.1%20ESub-afm72.mkv</link>
    <thumbnail>http://10.1.1.1/data/English%20Movies%20%281080p%29/%282011%29%201080p/War%20Horse%20%282011%29%201080p/a_AL_.jpg</thumbnail>
    <fanart>http://10.1.1.1/data/English%20Movies%20%281080p%29/%282011%29%201080p/War%20Horse%20%282011%29%201080p/a_AL_.jpg</fanart>
  </movie>
  <movie>
    <title>Warrior (2011)</title>
    <link>http://10.1.1.1/data/English%20Movies%20%281080p%29/%282011%29%201080p/Warrior%20%282011%29%201080p/Warrior%20%282011%29%201080p%20BluRay%20x265%20HEVC%2010bit%20AAC%205.1%20ESub-Vyndros.mkv</link>
    <thumbnail>http://10.1.1.1/data/English%20Movies%20%281080p%29/%282011%29%201080p/Warrior%20%282011%29%201080p/a_AL_.jpg</thumbnail>
    <fanart>http://10.1.1.1/data/English%20Movies%20%281080p%29/%282011%29%201080p/Warrior%20%282011%29%201080p/a_AL_.jpg</fanart>
  </movie>
  <movie>
    <title>Water for Elephants (2011)</title>
    <link>http://10.1.1.1/data/English%20Movies%20%281080p%29/%282011%29%201080p/Water%20for%20Elephants%20%282011%29%201080p/Water.For.Elephants.2011.1080p.BluRay.H264.AAC-RARBG.mp4</link>
    <thumbnail>http://10.1.1.1/data/English%20Movies%20%281080p%29/%282011%29%201080p/Water%20for%20Elephants%20%282011%29%201080p/a_AL_.jpg</thumbnail>
    <fanart>http://10.1.1.1/data/English%20Movies%20%281080p%29/%282011%29%201080p/Water%20for%20Elephants%20%282011%29%201080p/a_AL_.jpg</fanart>
  </movie>
  <movie>
    <title>We Bought a Zoo (2011)</title>
    <link>http://10.1.1.1/data/English%20Movies%20%281080p%29/%282011%29%201080p/We%20Bought%20a%20Zoo%20%282011%29%201080p/We.Bought.a.Zoo.2011.1080p.BluRay.x264.5.1-NVEE.mp4</link>
    <thumbnail>http://10.1.1.1/data/English%20Movies%20%281080p%29/%282011%29%201080p/We%20Bought%20a%20Zoo%20%282011%29%201080p/a_AL_.jpg</thumbnail>
    <fanart>http://10.1.1.1/data/English%20Movies%20%281080p%29/%282011%29%201080p/We%20Bought%20a%20Zoo%20%282011%29%201080p/a_AL_.jpg</fanart>
  </movie>
  <movie>
    <title>We Need to Talk About Kevin (2011)</title>
    <link>http://10.1.1.1/data/English%20Movies%20%281080p%29/%282011%29%201080p/We%20Need%20to%20Talk%20About%20Kevin%20%282011%29%201080p/We%20Need%20to%20Talk%20About%20Kevin%20%282011%29%201080p%20BluRay%20x265%20HEVC%20AAC%205.1%20MSubs-Silence.mkv</link>
    <thumbnail>http://10.1.1.1/data/English%20Movies%20%281080p%29/%282011%29%201080p/We%20Need%20to%20Talk%20About%20Kevin%20%282011%29%201080p/a_AL_.jpg</thumbnail>
    <fanart>http://10.1.1.1/data/English%20Movies%20%281080p%29/%282011%29%201080p/We%20Need%20to%20Talk%20About%20Kevin%20%282011%29%201080p/a_AL_.jpg</fanart>
  </movie>
  <movie>
    <title>Wrong Turn 4-Bloody Beginnings (2011)</title>
    <link>http://10.1.1.1/data/English%20Movies%20%281080p%29/%282011%29%201080p/Wrong%20Turn%204-Bloody%20Beginnings%20%282011%29%201080p/Wrong%20Turn%204-Bloody%20Beginnings%20%282011%29%201080p%20BluRay%20x265%20HEVC%2010bit%20AAC%205.1%20MSubs-Tigole.mkv</link>
    <thumbnail>http://10.1.1.1/data/English%20Movies%20%281080p%29/%282011%29%201080p/Wrong%20Turn%204-Bloody%20Beginnings%20%282011%29%201080p/a_AL_.jpg</thumbnail>
    <fanart>http://10.1.1.1/data/English%20Movies%20%281080p%29/%282011%29%201080p/Wrong%20Turn%204-Bloody%20Beginnings%20%282011%29%201080p/a_AL_.jpg</fanart>
  </movie>
  <movie>
    <title>X-Men - First Class (2011)</title>
    <link>http://10.1.1.1/data/English%20Movies%20%281080p%29/%282011%29%201080p/X-Men%20-%20First%20Class%20%282011%29%201080p%20%5BDual%20Audio%5D/X-Men%20First%20Class%20%282011%29%201080p%20BluRay%20x265%20HEVC%20ESub%20%5BDual%20Audio%5D%5BHindi%205.1%2BEnglish%205.1%5D%20-OlaM.mkv</link>
    <thumbnail>http://10.1.1.1/data/English%20Movies%20%281080p%29/%282011%29%201080p/X-Men%20-%20First%20Class%20%282011%29%201080p%20%5BDual%20Audio%5D/a_AL_.jpg</thumbnail>
    <fanart>http://10.1.1.1/data/English%20Movies%20%281080p%29/%282011%29%201080p/X-Men%20-%20First%20Class%20%282011%29%201080p%20%5BDual%20Audio%5D/a_AL_.jpg</fanart>
  </movie>
  <movie>
    <title>X-Night of Vengeance (2011)</title>
    <link>http://10.1.1.1/data/English%20Movies%20%281080p%29/%282011%29%201080p/X-Night%20of%20Vengeance%20%282011%29%201080p/X.Night.of.Vengeance.2011.1080p.BluRay.x264.YIFY.mp4</link>
    <thumbnail>http://10.1.1.1/data/English%20Movies%20%281080p%29/%282011%29%201080p/X-Night%20of%20Vengeance%20%282011%29%201080p/a29.jpg</thumbnail>
    <fanart>http://10.1.1.1/data/English%20Movies%20%281080p%29/%282011%29%201080p/X-Night%20of%20Vengeance%20%282011%29%201080p/a29.jpg</fanart>
  </movie>
  <movie>
    <title>Young Adult (2011)</title>
    <link>http://10.1.1.1/data/English%20Movies%20%281080p%29/%282011%29%201080p/Young%20Adult%20%282011%29%201080p%20%5BDual%20Audio%5D/Young%20Adult%20%282011%29%201080p%20BluRay%20x265%20HEVC%20MSubs%20%5BDual%20Audio%5D%5BHindi%205.1%2BEnglish%205.1%5D%20-mkvC.mkv</link>
    <thumbnail>http://10.1.1.1/data/English%20Movies%20%281080p%29/%282011%29%201080p/Young%20Adult%20%282011%29%201080p%20%5BDual%20Audio%5D/a_AL_.jpg</thumbnail>
    <fanart>http://10.1.1.1/data/English%20Movies%20%281080p%29/%282011%29%201080p/Young%20Adult%20%282011%29%201080p%20%5BDual%20Audio%5D/a_AL_.jpg</fanart>
  </movie>
</movies>
